<?xml version="1.0" encoding="UTF-8"?><!-- This file was auto-generated from WSDL --><!-- by the Apache Axis2 version: 1.6.2  Built on : Apr 17, 2012 (05:33:49 IST) --><serviceGroup>
    <service name="EmployeeProfileService">
        <messageReceivers>
            <messageReceiver mep="http://www.w3.org/ns/wsdl/in-out" class="com.msjava.webservice.EmployeeProfileServiceMessageReceiverInOut"/>
        </messageReceivers>
        <parameter name="ServiceClass">com.msjava.webservice.EmployeeProfileServiceSkeleton</parameter>
        <parameter name="useOriginalwsdl">true</parameter>
        <parameter name="modifyUserWSDLPortAddress">true</parameter>
        <operation name="GetEmployeeProfile" mep="http://www.w3.org/ns/wsdl/in-out" namespace="http://msjavasolutions.com/employeeProfile">
            <actionMapping>urn:GetEmployeeProfile</actionMapping>
            <outputActionMapping>http://msjavasolutions.com/employeeProfile/EmployeeProfilePortType/GetEmployeeProfileResponse</outputActionMapping>
        </operation>
    </service>
</serviceGroup>
